README.rst
setup.py
vcab/__init__.py
vcab/app.py
vcab/commands.py
vcab/config.py
vcab/message.py
vcab.egg-info/PKG-INFO
vcab.egg-info/SOURCES.txt
vcab.egg-info/dependency_links.txt
vcab.egg-info/requires.txt
vcab.egg-info/top_level.txt