Metadata-Version: 1.0
Name: vcab
Version: 1.0.0
Summary: Bridge tool to connect VCP and absinthe
Home-page: https://github.com/voidpp/vcab.git
Author: Lajos Santa
Author-email: santa.lajos@coldline.hu
License: MIT
Platform: UNKNOWN
